datacore_sdk/__init__.py
datacore_sdk/cli.py
datacore_sdk/client.py
datacore_sdk/exceptions.py
datacore_sdk/http.py
datacore_sdk/types.py
datacore_sdk/endpoints/projects.py
datacore_sdk_python-0.1.0.dist-info/METADATA
datacore_sdk_python-0.1.0.dist-info/WHEEL
datacore_sdk_python-0.1.0.dist-info/entry_points.txt
datacore_sdk_python-0.1.0.dist-info/top_level.txt
datacore_sdk_python-0.1.0.dist-info/RECORD
