Metadata-Version: 2.4
Name: datacore-sdk-python
Version: 0.1.0
Summary: Python SDK skeleton for Tachyus DataCore API
Author-email: Tachyus <jose.guzman@tachyus.com>
License: MIT
Project-URL: Homepage, https://example.com/datacore-sdk-python
Project-URL: Repository, https://example.com/datacore-sdk-python.git
Requires-Python: >=3.9
Requires-Dist: requests>=2.31
